LICENSE
MANIFEST.in
README.rst
requirements.txt
setup.py
Flask_Dashboard.egg-info/PKG-INFO
Flask_Dashboard.egg-info/SOURCES.txt
Flask_Dashboard.egg-info/dependency_links.txt
Flask_Dashboard.egg-info/not-zip-safe
Flask_Dashboard.egg-info/requires.txt
Flask_Dashboard.egg-info/top_level.txt
flask_dashboard/__init__.py
flask_dashboard/actions.py
flask_dashboard/base.py
flask_dashboard/helpers.py
flask_dashboard/contrib/__init__.py
flask_dashboard/contrib/sqla/__init__.py
flask_dashboard/contrib/sqla/ajax.py
flask_dashboard/contrib/sqla/fields.py
flask_dashboard/contrib/sqla/filters.py
flask_dashboard/contrib/sqla/tools.py
flask_dashboard/contrib/sqla/view.py
flask_dashboard/form/__init__.py
flask_dashboard/form/fields.py
flask_dashboard/form/widgets.py
flask_dashboard/model/__init__.py
flask_dashboard/model/base.py
flask_dashboard/model/fields.py
flask_dashboard/model/template.py