Metadata-Version: 1.1
Name: Flask-Dashboard
Version: 0.0.6a
Summary: Yet another admin interface for Flask
Home-page: UNKNOWN
Author: Cosmia Fu
Author-email: cosmiafu@gmail.com
License: BSD
Platform: UNKNOWN
Classifier: Development Status :: 2 - Pre-Alpha
Classifier: Environment :: Web Environment
Classifier: Intended Audience :: Developers
Classifier: License :: OSI Approved :: ISC License (ISCL)
Classifier: Operating System :: OS Independent
Classifier: Programming Language :: Python
